django_github_webhook/__init__.py
django_github_webhook/views.py
django_github_webhook-0.1.1.dist-info/DESCRIPTION.rst
django_github_webhook-0.1.1.dist-info/METADATA
django_github_webhook-0.1.1.dist-info/RECORD
django_github_webhook-0.1.1.dist-info/WHEEL
django_github_webhook-0.1.1.dist-info/metadata.json
django_github_webhook-0.1.1.dist-info/top_level.txt
