Metadata-Version: 1.1
Name: django-github-webhook
Version: 0.1.1
Summary: Django view for GitHub webhook recievers
Home-page: https://github.com/fladi/django-github-webhook
Author: Michael Fladischer
Author-email: michael@openservices.at
License: BSD
Keywords: django,view,github,webhook,signature
Platform: UNKNOWN
Classifier: Development Status :: 5 - Production/Stable
Classifier: Intended Audience :: Developers
Classifier: License :: OSI Approved :: BSD License
Classifier: Programming Language :: Python
Classifier: Programming Language :: Python :: 3
Classifier: Programming Language :: Python :: 3.4
Classifier: Programming Language :: Python :: 3.5
Classifier: Programming Language :: Python :: Implementation :: CPython
Classifier: Programming Language :: Python :: Implementation :: PyPy
Classifier: Topic :: Utilities
